ipyprompt/__init__.py
ipyprompt/prompt.py
ipyprompt-0.0.1.dist-info/METADATA
ipyprompt-0.0.1.dist-info/RECORD
ipyprompt-0.0.1.dist-info/WHEEL
ipyprompt-0.0.1.dist-info/top_level.txt
