Metadata-Version: 2.1
Name: ipyprompt
Version: 0.0.1
Summary: Custom IPython prompt with execution time included
Home-page: https://github.com/luyiming/ipyprompt
Author: luyiming
Author-email: luyimingchn@gmail.com
License: UNKNOWN
Keywords: ipython,jupyter,extension
Platform: UNKNOWN
